{
  "routes": [
    {
      "method": "GET",
      "path": "/certyfikaty",
      "handler": "certyfikaty.find",
      "config": {
        "policies": []
      }
    },
    {
      "method": "GET",
      "path": "/certyfikaty/count",
      "handler": "certyfikaty.count",
      "config": {
        "policies": []
      }
    },
    {
      "method": "GET",
      "path": "/certyfikaty/:id",
      "handler": "certyfikaty.findOne",
      "config": {
        "policies": []
      }
    },
    {
      "method": "POST",
      "path": "/certyfikaty",
      "handler": "certyfikaty.create",
      "config": {
        "policies": []
      }
    },
    {
      "method": "PUT",
      "path": "/certyfikaty/:id",
      "handler": "certyfikaty.update",
      "config": {
        "policies": []
      }
    },
    {
      "method": "DELETE",
      "path": "/certyfikaty/:id",
      "handler": "certyfikaty.delete",
      "config": {
        "policies": []
      }
    }
  ]
}
